c1v_id/__init__.py
c1v_id/blocking.py
c1v_id/clustering.py
c1v_id/config.py
c1v_id/golden.py
c1v_id/normalize.py
c1v_id/py.typed
c1v_id/resolver.py
c1v_id/scoring.py
c1v_id-0.1.0.dist-info/METADATA
c1v_id-0.1.0.dist-info/WHEEL
c1v_id-0.1.0.dist-info/licenses/LICENSE
c1v_id-0.1.0.dist-info/RECORD
