Metadata-Version: 2.4
Name: c1v-id
Version: 0.1.0
Summary: Identity resolution for AI applications - resolve duplicates in 10 lines of Python
Project-URL: Homepage, https://github.com/davidancor/c1v-id
Project-URL: Documentation, https://github.com/davidancor/c1v-id#readme
Project-URL: Repository, https://github.com/davidancor/c1v-id
Project-URL: Issues, https://github.com/davidancor/c1v-id/issues
Author: David Ancor
License-Expression: MIT
License-File: LICENSE
Keywords: ai,deduplication,entity-matching,golden-record,identity-resolution,langchain,mcp,record-linkage
Classifier: Development Status :: 3 - Alpha
Classifier: Intended Audience :: Developers
Classifier: License :: OSI Approved :: MIT License
Classifier: Operating System :: OS Independent
Classifier: Programming Language :: Python :: 3
Classifier: Programming Language :: Python :: 3.10
Classifier: Programming Language :: Python :: 3.11
Classifier: Programming Language :: Python :: 3.12
Classifier: Programming Language :: Python :: 3.13
Classifier: Topic :: Scientific/Engineering :: Artificial Intelligence
Classifier: Typing :: Typed
Requires-Python: >=3.10
Requires-Dist: pandas>=2.0.0
Requires-Dist: pyyaml>=6.0
Requires-Dist: rapidfuzz>=3.0.0
Provides-Extra: dev
Requires-Dist: mypy>=1.0.0; extra == 'dev'
Requires-Dist: pytest-cov>=4.0.0; extra == 'dev'
Requires-Dist: pytest>=7.0.0; extra == 'dev'
Requires-Dist: ruff>=0.1.0; extra == 'dev'
